darca_file_utils/__init__.py
darca_file_utils/__version__.py
darca_file_utils/directory_utils.py
darca_file_utils/file_utils.py
darca_file_utils-0.1.1.dist-info/LICENSE
darca_file_utils-0.1.1.dist-info/METADATA
darca_file_utils-0.1.1.dist-info/WHEEL
darca_file_utils-0.1.1.dist-info/RECORD
